README.md
setup.py
dirmap/__init__.py
dirmap/core.py
dirmap/deep.py
dirmap.egg-info/PKG-INFO
dirmap.egg-info/SOURCES.txt
dirmap.egg-info/dependency_links.txt
dirmap.egg-info/top_level.txt
dirmap/altcores/__init__.py
dirmap/altcores/deferredre.py
dirmap/altcores/dictlookup.py
dirmap/altcores/dicttrie.py
dirmap/altcores/immediatere.py