Metadata-Version: 1.1
Name: dirmap
Version: 0.1.0
Summary: Directory remapper.
Home-page: http://github.com/vfxetc/dirmap
Author: Mike Boers
Author-email: floss+dirmap@vfxetc.com
License: BSD-3
Platform: UNKNOWN
Classifier: Intended Audience :: Developers
Classifier: License :: OSI Approved :: BSD License
Classifier: Natural Language :: English
Classifier: Operating System :: OS Independent
Classifier: Programming Language :: Python :: 2
Classifier: Topic :: Software Development :: Libraries :: Python Modules
